bin/__init__.py
cluttermanager/__init__.py
cluttermanager/bindings.py
cluttermanager-0.4.7.data/scripts/cluttermanager
cluttermanager-0.4.7.dist-info/LICENSE
cluttermanager-0.4.7.dist-info/METADATA
cluttermanager-0.4.7.dist-info/WHEEL
cluttermanager-0.4.7.dist-info/top_level.txt
cluttermanager-0.4.7.dist-info/RECORD
