Metadata-Version: 2.1
Name: cluttermanager
Version: 0.4.7
Summary: Clutter Manager for your folders
Home-page: https://github.com/puneet29/ClutterManager
Author: Puneet Saini
Author-email: puneet29saini@gmail.com
License: UNKNOWN
Platform: UNKNOWN
